kam12filereader/__init__.py
kam12filereader/exceptions.py
kam12filereader/hidden_operation.py
kam12filereader/main_operation.py
kam12filereader/static_object.py
kam12filereader-3.1.dist-info/LICENCE
kam12filereader-3.1.dist-info/METADATA
kam12filereader-3.1.dist-info/WHEEL
kam12filereader-3.1.dist-info/top_level.txt
kam12filereader-3.1.dist-info/RECORD
